{
  "term": "Spring",
  "year": "2001",
  "level": [
    "Undergraduate"
  ],
  "topics": [
    [
      "Science",
      "Cognitive Science"
    ],
    [
      "Science",
      "Biology",
      "Genetics"
    ],
    [
      "Science",
      "Biology",
      "Neuroscience"
    ],
    [
      "Social Science",
      "Psychology"
    ]
  ],
  "legacy_uid": "27063ed8-6210-6065-5f70-0952188a99c0",
  "instructors": {
    "content": [
      "335fc995-6d6e-1c24-6a25-5715fa17f765",
      "d8e238b9-572a-1350-b105-64bcc323d658"
    ],
    "website": "ocw-www"
  },
  "course_image": {
    "content": "77520d67-cd6e-7b3d-e704-f953fbd72abf",
    "website": "9-19j-cognitive-behavioral-genetics-spring-2001"
  },
  "course_title": "Cognitive & Behavioral Genetics",
  "hide_download": true,
  "course_description": "How genetics can add to our understanding of cognition, language, emotion, personality, and behavior. Use of gene mapping to estimate risk factors for psychological disorders and variation in behavioral and personality traits. Mendelian genetics, genetic mapping techniques, and statistical analysis of large populations and their application to particular studies in behavioral genetics. Topics also include environmental influence on genetic programs, evolutionary genetics, and the larger scientific, social, ethical, and philosophical implications.\n",
  "department_numbers": [
    "9",
    "7"
  ],
  "extra_course_numbers": "9.191,7.66J",
  "primary_course_number": "9.19J",
  "course_image_thumbnail": {
    "content": "be3a17d9-a462-b5d4-1be6-176775575a8a",
    "website": "9-19j-cognitive-behavioral-genetics-spring-2001"
  },
  "hide_download_original": true,
  "learning_resource_types": [
    "Written Assignments"
  ],
  "site_uid": "7b7eef0e-422b-4495-8209-03e1cad3c653",
  "site_short_id": "9.19j-spring-2001",
  "site_url_path": "courses/9-19j-cognitive-behavioral-genetics-spring-2001",
  "title": "Course Metadata"
}